Metadata-Version: 1.1
Name: ongair-yowsup2
Version: 2.4.48.19
Summary: A WhatsApp python library
Home-page: http://github.com/tgalal/yowsup/
Author: Tarek Galal
Author-email: tare2.galal@gmail.com
License: GPL-3+
Platform: any
Classifier: Programming Language :: Python
Classifier: Development Status :: 4 - Beta
Classifier: Natural Language :: English
Classifier: Intended Audience :: Developers
Classifier: License :: OSI Approved :: GNU General Public License v3 or later (GPLv3+)
Classifier: Operating System :: OS Independent
Classifier: Topic :: Software Development :: Libraries :: Python Modules
